[
  {
    "intent": "time",
    "keywords": ["كم الساعة", "الساعة الان", "الساعة الآن", "ما هو الوقت", "الوقت الحالي", "قداش الوقت", "اعطني الوقت", "وقتاش"],
    "type": "dynamic"
  },
  {
    "intent": "date",
    "keywords": ["ما هو تاريخ اليوم", "تاريخ اليوم", "اليوم كام في الشهر", "شنوة تاريخ اليوم", "كم التاريخ", "اي يوم نحن", "ما يوم اليوم"],
    "type": "dynamic"
  },
  {
    "intent": "greeting",
    "keywords": ["مرحبا", "السلام عليكم", "اهلا", "صباح الخير", "مساء الخير", "عسلامة", "هلو"],
    "response": "وعليكم السلام ورحمة الله! 👋 أنا **العقل التونسي**، مساعدك الذكاء الاصطناعي. كيف يمكنني إفادتك اليوم؟",
    "type": "static"
  },
  {
    "intent": "creator",
    "keywords": ["من صنعك", "من برمجك", "كيف تم تطويرك", "من هو مطورك", "من الذي انشاك", "من هو صانعك", "من يملكك"],
    "response": "تمت صناعتي وتطويري على يد **شاب تونسي** من جنوب البلاد يبلغ من العمر **16 سنة**. 🇹🇳",
    "type": "static"
  },
  {
    "intent": "whoami",
    "keywords": ["من انت", "من تكون", "تعريف العقل التونسي", "عرف بنفسك", "هل انت بيتر", "هل انت جي بي تي", "شو اسمك", "ما اسمك"],
    "response": "أنا **العقل التونسي (Tunisia Mind AI)**، نظام ذكاء اصطناعي متقدم صُمِّم لمساعدتك في الإجابة على أسئلتك، البرمجة، التعلم، وحل المشاكل اليومية. 🧠",
    "type": "static"
  },
  {
    "intent": "tunisia_area_population",
    "keywords": ["مساحة تونس", "عدد سكان تونس", "سكان تونس", "كم مساحة", "كم عدد سكان تونس"],
    "response": "🇹🇳 **الجمهورية التونسية — معلومات أساسية:**\n\n- **المساحة:** 163,610 كم² (تحتل المرتبة 91 عالمياً)\n- **عدد السكان:** حوالي **12 مليون نسمة** (2024)\n- **العاصمة:** تونس العاصمة\n- **اللغة الرسمية:** العربية\n- **العملة:** الدينار التونسي (TND)\n- **الاستقلال:** 20 مارس 1956 عن فرنسا\n- **الدين الرسمي:** الإسلام\n- **النظام السياسي:** جمهورية رئاسية\n- **الموقع الجغرافي:** شمال أفريقيا، تحدها الجزائر غرباً وليبيا شرقاً والبحر الأبيض المتوسط شمالاً",
    "type": "static"
  },
  {
    "intent": "tunisia_info",
    "keywords": ["معلومات عن تونس", "تاريخ تونس", "عاصمة تونس", "متى استقلت تونس", "تونس الخضراء", "اين تقع تونس", "عن تونس"],
    "response": "🇹🇳 **تونس — لمحة شاملة:**\n\n- **الاسم الرسمي:** الجمهورية التونسية\n- **الموقع:** شمال أفريقيا على ساحل البحر الأبيض المتوسط\n- **المساحة:** 163,610 كم²\n- **السكان:** ~12 مليون نسمة (2024)\n- **العاصمة:** تونس\n- **اللغة:** العربية (رسمية) + الفرنسية (واسعة الاستخدام)\n- **الاستقلال:** 20 مارس 1956\n- **الحضارة:** موطن قرطاج (أحد أعظم حضارات العالم القديم)\n- **المعالم:** الجامع الأعظم بالقيروان، الكولوسيوم في الجم، المدينة العتيقة بتونس (تراث يونسكو)\n- **الاقتصاد:** سياحة، فوسفات، زيت زيتون، صناعات خفيفة",
    "type": "static"
  }
]
